db_utils.py
file_utils.py
linshenghua-0.1.7.dist-info/METADATA
linshenghua-0.1.7.dist-info/WHEEL
linshenghua-0.1.7.dist-info/top_level.txt
linshenghua-0.1.7.dist-info/RECORD
