Metadata-Version: 2.1
Name: linshenghua
Version: 0.1.7
Summary: some moudles for python user
Author: linshenghua
Author-email: 780141734@qq.com
Classifier: Programming Language :: Python :: 3
Classifier: License :: OSI Approved :: MIT License
Classifier: Operating System :: OS Independent
